README.rst
setup.py
relevance/__init__.py
relevance/document.py
relevance/facet.py
relevance/loggers.py
relevance/manager.py
relevance/mapping.py
relevance/query.py
relevance/service.py
relevance/settings.py
relevance.egg-info/PKG-INFO
relevance.egg-info/SOURCES.txt
relevance.egg-info/dependency_links.txt
relevance.egg-info/entry_points.txt
relevance.egg-info/requires.txt
relevance.egg-info/top_level.txt
relevance/engine/__init__.py
relevance/engine/elastic.py
relevance/search/__init__.py
relevance/search/service.py
relevance/utils/__init__.py
relevance/utils/cli.py