Metadata-Version: 1.2
Name: relevance
Version: 0.4.6
Summary: Relevance, Full-stack search engine, core module.
Home-page: http://www.relevance.io
Author: Francis Lacroix
Author-email: f@overridelogic.com
License: MIT
Platform: any
Classifier: Development Status :: 3 - Alpha
Classifier: Environment :: Console
Classifier: Intended Audience :: Information Technology
Classifier: Intended Audience :: Developers
Classifier: Intended Audience :: Science/Research
Classifier: Intended Audience :: System Administrators
Classifier: License :: OSI Approved :: MIT License
Classifier: Operating System :: OS Independent
Classifier: Programming Language :: Python :: 3
Classifier: Topic :: Internet :: WWW/HTTP :: Indexing/Search
Provides: relevance
Requires-Python: >=3.5
